Metadata-Version: 1.0
Name: ulam-number
Version: 1.0.0
Summary: Это пакет для нахождения последовательности чисел Улама
Home-page: UNKNOWN
Author: Мочалов Семён
Author-email: semenmochalov55@gmai.com
License: UNKNOWN
Platform: UNKNOWN
